[
  {
    "text": "boa noite Quais as opções por gentileza? valeu",
    "intent": "ask_pizza",
    "intent_prediction": {
      "name": "ask_menu",
      "confidence": 0.3100389540195465
    }
  },
  {
    "text": "O que vocês tem?",
    "intent": "ask_menu",
    "intent_prediction": {
      "name": "ask_drink",
      "confidence": 0.5992611646652222
    }
  },
  {
    "text": "Quais as opções?",
    "intent": "ask_menu",
    "intent_prediction": {
      "name": "ask_pizza",
      "confidence": 0.4102635979652405
    }
  },
  {
    "text": "Quais as opções disponíveis?",
    "intent": "ask_menu",
    "intent_prediction": {
      "name": "ask_drink",
      "confidence": 0.7790648937225342
    }
  },
  {
    "text": "não",
    "intent": "negate",
    "intent_prediction": {
      "name": "mood_unhappy",
      "confidence": 0.5786051750183105
    }
  },
  {
    "text": "nao",
    "intent": "negate",
    "intent_prediction": {
      "name": "affirm",
      "confidence": 0.23051457107067108
    }
  },
  {
    "text": "bom",
    "intent": "mood_great",
    "intent_prediction": {
      "name": "goodbye",
      "confidence": 0.3422080874443054
    }
  }
]